Coordconv-1.0.0.data/scripts/cli.py
Coordconv-1.0.0.dist-info/DESCRIPTION.rst
Coordconv-1.0.0.dist-info/METADATA
Coordconv-1.0.0.dist-info/RECORD
Coordconv-1.0.0.dist-info/WHEEL
Coordconv-1.0.0.dist-info/entry_points.txt
Coordconv-1.0.0.dist-info/metadata.json
Coordconv-1.0.0.dist-info/top_level.txt
Coordsys/__init__.py
Coordsys/cli.py
